indstocks/__init__.py
indstocks/quote.py
indstocks/scrapers/__init__.py
indstocks/scrapers/investing.py
indstocks/scrapers/links.json
indstocks/scrapers/moneycontrol.py
indstocks/scrapers/screener.py
indstocks/scrapers/data/__init__.py
indstocks/scrapers/data/links.py
indstocks-1.1.1.dist-info/LICENSE
indstocks-1.1.1.dist-info/METADATA
indstocks-1.1.1.dist-info/WHEEL
indstocks-1.1.1.dist-info/top_level.txt
indstocks-1.1.1.dist-info/RECORD
