Metadata-Version: 2.1
Name: indstocks
Version: 1.1.1
Summary: Access to Indian Stock Market insights via Python package.
Home-page: https://github.com/theadityareddy/indstocks
Author: Aditya Reddy & Kshitij Mahale
Author-email: adityareddy.biz@gmail.com, kshitijmahale02@gmail.com
License: MIT
Keywords: python,india,nse,bse,stock market,indian,data scraper
Classifier: Development Status :: 4 - Beta
Classifier: Intended Audience :: Developers
Classifier: Intended Audience :: Financial and Insurance Industry
Classifier: License :: OSI Approved :: MIT License
Classifier: Topic :: Office/Business :: Financial
Classifier: Programming Language :: Python :: 3
Classifier: Operating System :: OS Independent
Requires-Python: >=3.10
License-File: LICENSE
Requires-Dist: beautifulsoup4
Requires-Dist: bs4
Requires-Dist: requests
Requires-Dist: selenium
Provides-Extra: dev
Requires-Dist: pytest>7.0; extra == "dev"
Requires-Dist: twine>4.0.2; extra == "dev"
